CslBot-0.21.dist-info/DESCRIPTION.rst
CslBot-0.21.dist-info/METADATA
CslBot-0.21.dist-info/RECORD
CslBot-0.21.dist-info/WHEEL
CslBot-0.21.dist-info/entry_points.txt
CslBot-0.21.dist-info/metadata.json
CslBot-0.21.dist-info/top_level.txt
cslbot/__init__.py
cslbot/alembic/env.py
cslbot/alembic/script.py.mako
cslbot/alembic/versions/243c9cf0eb7d_use_datetime_not_float.py
cslbot/alembic/versions/2ee084539c59_no_timezones.py
cslbot/alembic/versions/3614b38ddf9_kick_logging_change.py
cslbot/alembic/versions/385c29e42d9_remove_nicks.py
cslbot/alembic/versions/4d165186b4ed_fix_nullable.py
cslbot/alembic/versions/55efdbb748c_merge_pending.py
cslbot/alembic/versions/7fde00129eb6_multi_babble.py
cslbot/alembic/versions/e7106eedcf8c_fix_stopwatch.py
cslbot/alembic/versions/ef7ccebeff_initial_commit.py
cslbot/commands/8ball.py
cslbot/commands/__init__.py
cslbot/commands/about.py
cslbot/commands/abuse.py
cslbot/commands/acl.py
cslbot/commands/acronym.py
cslbot/commands/active.py
cslbot/commands/admins.py
cslbot/commands/babble.py
cslbot/commands/bard.py
cslbot/commands/bc.py
cslbot/commands/bike.py
cslbot/commands/blame.py
cslbot/commands/botsnack.py
cslbot/commands/botspam.py
cslbot/commands/cadmin.py
cslbot/commands/cancel.py
cslbot/commands/channels.py
cslbot/commands/choose.py
cslbot/commands/cidr.py
cslbot/commands/coin.py
cslbot/commands/cve.py
cslbot/commands/ddate.py
cslbot/commands/defersay.py
cslbot/commands/define.py
cslbot/commands/demorse.py
cslbot/commands/distro.py
cslbot/commands/dvorak.py
cslbot/commands/ebay.py
cslbot/commands/eix.py
cslbot/commands/errno.py
cslbot/commands/filter.py
cslbot/commands/fml.py
cslbot/commands/fortune.py
cslbot/commands/fullwidth.py
cslbot/commands/fweather.py
cslbot/commands/gcc.py
cslbot/commands/gizoogle.py
cslbot/commands/google.py
cslbot/commands/grep.py
cslbot/commands/guarded.py
cslbot/commands/help.py
cslbot/commands/highlight.py
cslbot/commands/hooks.py
cslbot/commands/ignore.py
cslbot/commands/imdb.py
cslbot/commands/inspect.py
cslbot/commands/insult.py
cslbot/commands/intensify.py
cslbot/commands/ipa.py
cslbot/commands/issue.py
cslbot/commands/isup.py
cslbot/commands/jargon.py
