Metadata-Version: 2.0
Name: CslBot
Version: 0.21
Summary: An easily extensible, modular irc bot.
Home-page: https://github.com/tjcsl/cslbot
Author: The TJHSST Computer Systems Lab
Author-email: cslbot@pefoley.com
License: GPL
Keywords: csl,tjhsst,tj,irc,bot
Platform: UNKNOWN
Classifier: Development Status :: 4 - Beta
Classifier: License :: OSI Approved :: GNU General Public License v2 or later (GPLv2+)
Classifier: Programming Language :: Python :: 3.5
Classifier: Topic :: Communications :: Chat :: Internet Relay Chat
Requires-Dist: SQLAlchemy (>=1.0.0)
Requires-Dist: alembic
Requires-Dist: geoip2
Requires-Dist: irc (>=12.2)
Requires-Dist: jinja2
Requires-Dist: lxml
Requires-Dist: mypy-lang
Requires-Dist: python-dateutil
Requires-Dist: requests (>=2.4.0)
Requires-Dist: requests-oauthlib
Requires-Dist: simplejson
Requires-Dist: sphinx
Provides-Extra: analysis
Requires-Dist: autopep8; extra == 'analysis'
Requires-Dist: docformatter; extra == 'analysis'
Requires-Dist: flake8-coding; extra == 'analysis'
Requires-Dist: flake8-debugger; extra == 'analysis'
Requires-Dist: flake8-import-order; extra == 'analysis'
Requires-Dist: flake8-string-format; extra == 'analysis'
Requires-Dist: pep8-naming; extra == 'analysis'
Requires-Dist: radon; extra == 'analysis'
Provides-Extra: test
Requires-Dist: pytest-xdist; extra == 'test'
